twitchirc/__init__.py
twitchirc/argument_parser.py
twitchirc/bot.py
twitchirc/bot_storage.py
twitchirc/command.py
twitchirc/connection.py
twitchirc/debug_bot.py
twitchirc/log.py
twitchirc/logging.py
twitchirc/messages.py
twitchirc/middleware.py
twitchirc/moderation.py
twitchirc/patterns.py
twitchirc/permission_names.py
twitchirc/permissions.py
twitchirc/shell.py
twitchirc/stock_commands.py
twitchirc/utils.py
twitchirc-1.8.4.dist-info/METADATA
twitchirc-1.8.4.dist-info/WHEEL
twitchirc-1.8.4.dist-info/top_level.txt
twitchirc-1.8.4.dist-info/RECORD
