Metadata-Version: 2.1
Name: twitchirc
Version: 1.8.4
Summary: Unofficial library for Twitch irc.
Home-page: https://www.github.com/mm2pl/twitchirc
Author: mm2pl
Author-email: u.y@o2.pl
License: GPLv3
Platform: UNKNOWN
Requires-Python: >=3.7
